pyshard/__init__.py
pyshard/app/__init__.py
pyshard/app/app.py
pyshard/console/__init__.py
pyshard/console/pyshard.py
pyshard/core/client.py
pyshard/core/connect.py
pyshard/core/server.py
pyshard/core/typing.py
pyshard/master/__init__.py
pyshard/master/client.py
pyshard/master/master.py
pyshard/master/server.py
pyshard/settings/settings.py
pyshard/shard/__init__.py
pyshard/shard/client.py
pyshard/shard/database.py
pyshard/shard/monitoring.py
pyshard/shard/node.py
pyshard/shard/protocol.py
pyshard/shard/server.py
pyshard/shard/shard.py
pyshard/storage/__init__.py
pyshard/storage/base.py
pyshard/storage/errors.py
pyshard/storage/inmemory.py
pyshard/utils/__init__.py
pyshard-0.2.3.dist-info/LICENSE
pyshard-0.2.3.dist-info/METADATA
pyshard-0.2.3.dist-info/WHEEL
pyshard-0.2.3.dist-info/entry_points.txt
pyshard-0.2.3.dist-info/top_level.txt
pyshard-0.2.3.dist-info/RECORD
