Metadata-Version: 2.1
Name: pyshard
Version: 0.2.3
Summary: Distributed key-value storage in Python stdlib
Home-page: https://github.com/la9ran9e/pyshard
Author: la9ran9e
Author-email: tvauritimur@gmail.com
License: UNKNOWN
Platform: UNKNOWN
